ReactRumenjiaocheng/README.md
ReactRumenjiaocheng/__init__.py
ReactRumenjiaocheng/__main__.py
ReactRumenjiaocheng/file.epub
ReactRumenjiaocheng/index.html
ReactRumenjiaocheng/css/__init__.py
ReactRumenjiaocheng/css/annotations.css
ReactRumenjiaocheng/css/main.css
ReactRumenjiaocheng/css/normalize.css
ReactRumenjiaocheng/css/popup.css
ReactRumenjiaocheng/font/__init__.py
ReactRumenjiaocheng/font/fontello.eot
ReactRumenjiaocheng/font/fontello.svg
ReactRumenjiaocheng/font/fontello.ttf
ReactRumenjiaocheng/font/fontello.woff
ReactRumenjiaocheng/img/__init__.py
ReactRumenjiaocheng/img/annotator-glyph-sprite.png
ReactRumenjiaocheng/img/annotator-icon-sprite.png
ReactRumenjiaocheng/img/apple-touch-icon.png
ReactRumenjiaocheng/img/cancelfullscreen.png
ReactRumenjiaocheng/img/close.png
ReactRumenjiaocheng/img/fullscreen.png
ReactRumenjiaocheng/img/loader.gif
ReactRumenjiaocheng/img/menu-icon.png
ReactRumenjiaocheng/img/save.png
ReactRumenjiaocheng/img/saved.png
ReactRumenjiaocheng/img/settings-s.png
ReactRumenjiaocheng/img/settings.png
ReactRumenjiaocheng/img/star.png
ReactRumenjiaocheng/js/__init__.py
ReactRumenjiaocheng/js/epub.js
ReactRumenjiaocheng/js/epub.min.js
ReactRumenjiaocheng/js/epub.min.map
ReactRumenjiaocheng/js/hooks.min.js
ReactRumenjiaocheng/js/hooks.min.map
ReactRumenjiaocheng/js/reader.js
ReactRumenjiaocheng/js/reader.js.map
ReactRumenjiaocheng/js/reader.min.js
ReactRumenjiaocheng/js/reader.min.map
ReactRumenjiaocheng/js/hooks/__init__.py
ReactRumenjiaocheng/js/hooks/extensions/__init__.py
ReactRumenjiaocheng/js/hooks/extensions/highlight.js
ReactRumenjiaocheng/js/libs/__init__.py
ReactRumenjiaocheng/js/libs/jquery.min.js
ReactRumenjiaocheng/js/libs/localforage.min.js
ReactRumenjiaocheng/js/libs/screenfull.js
ReactRumenjiaocheng/js/libs/screenfull.min.js
ReactRumenjiaocheng/js/libs/zip.min.js
ReactRumenjiaocheng/js/plugins/__init__.py
ReactRumenjiaocheng/js/plugins/hypothesis.js
ReactRumenjiaocheng/js/plugins/search.js
react_rumenjiaocheng-2024.3.2.0.dist-info/METADATA
react_rumenjiaocheng-2024.3.2.0.dist-info/WHEEL
react_rumenjiaocheng-2024.3.2.0.dist-info/entry_points.txt
react_rumenjiaocheng-2024.3.2.0.dist-info/top_level.txt
react_rumenjiaocheng-2024.3.2.0.dist-info/RECORD
